pgsocr-0.1.5.dist-info/METADATA
pgsocr-0.1.5.dist-info/WHEEL
pgsocr-0.1.5.dist-info/entry_points.txt
pgsocr-0.1.5.dist-info/licenses/LICENSE
pgsocr/__init__.py
pgsocr/img_utils.py
pgsocr/main.py
pgsocr/pgsparser.py
pgsocr/supconvert.py
pgsocr/tesseract_ocr_engine.py
pgsocr/transformer_ocr_engines.py
pgsocr-0.1.5.dist-info/RECORD
