Metadata-Version: 2.1
Name: pgsocr
Version: 0.1.5
Summary: A command line utility for converting Blu-ray subs to SRT or ASS using AI Language Models.
Author-Email: pcpeasant <pcpeasant25@gmail.com>
License: MIT
Requires-Python: >=3.11
Requires-Dist: pillow>=10.4.0
Requires-Dist: tesserocr>=2.7.0
Requires-Dist: numpy>=2.0.0
Requires-Dist: tqdm>=4.66.4
Requires-Dist: torch>=2.3.1; extra == "lm"
Requires-Dist: torchvision>=0.18.1; extra == "lm"
Requires-Dist: torchaudio>=2.3.1; extra == "lm"
Requires-Dist: transformers>=4.41.2; extra == "lm"
Requires-Dist: einops>=0.8.0; extra == "lm"
Requires-Dist: timm>=1.0.7; extra == "lm"
Requires-Dist: bitsandbytes>=0.43.3; extra == "lm"
Provides-Extra: lm
